HimosoftSmsApiClient/__init__.py
HimosoftSmsApiClient/client.py
himosoft_sms_api_client-1.0.0.dist-info/licenses/LICENSE
himosoft_sms_api_client-1.0.0.dist-info/METADATA
himosoft_sms_api_client-1.0.0.dist-info/WHEEL
himosoft_sms_api_client-1.0.0.dist-info/top_level.txt
himosoft_sms_api_client-1.0.0.dist-info/RECORD
